Proyecto Circuitos digitales/Proyecto/source/PARTE1/FFD_enable_estruc.v
//FF tipo D con enable activo en bajo
module DFF_enable_negado(
    input wire clk, en, 
    input d, 
    output wire q,q_n //Q y Q NEGADA
);
//Se baso en el diagrama para crear las conexiones entre cada compuerta 

wire not1_out, not2_out, nand1_out, nand2_out, nand3_out, nand4_out;
wire and1_out, and2_out, or1_out;

wire not3_out, not4_out, nand11_out, nand33_out;

not NOT3(not3_out, clk); //clock negado
//Enable
not NOT1(not1_out, en);
and AND1(and1_out, d, not1_out);
and AND2(and2_out, en, q);
or OR1(or1_out, and1_out, and2_out);
//Primer latch
not NOT2(not2_out, or1_out);
nand NAND1(nand1_out, or1_out, not3_out);
nand NAND3(nand3_out, not2_out, not3_out);
nand NAND2(nand2_out, nand1_out, nand4_out);
nand NAND4(nand4_out, nand3_out, nand2_out);
//Segundo latch
not NOT44(not4_out, nand2_out);
nand NAND11(nand11_out, nand2_out, clk);
nand NAND33(nand33_out, not4_out, clk);
nand NAND22(q, nand11_out, q_n);
nand NAND44(q_n, nand33_out, q);


//Fin

endmodule

Proyecto Circuitos digitales/source/PARTE1/FFD_enable.v
module BasicDFF_enable(
    input wire clk, en, 
    input d, 
    output reg q //No se ocupa q negada pero si se requiere solo lo agregamos y sera ~q
);
always @(posedge clk) //Cada flanco creciente activarse
    begin
        if (en == 0) q <= d;//Si en esta en bajo, se activa el flip flop
        else q=q; //De lo contrario no cambios
    end
endmodule

Proyecto Circuitos digitales/source/PARTE1/FFD_enable_tb.v
`include "FFD_enable.v"
`include "FFD_enable_estruc.v"
`timescale 1ns/1ns

module FFD_enable_tb;
    reg clk, en;
    reg d;
    wire q,q_n;

always begin
        clk = 1'b1; #1; // 20s en alto
        clk = 1'b0; #1; // 20s en bajo
end
always begin
        en = 1'b1; #3; // 20s en alto
        en = 1'b0; #3; // 20s en bajo
end

//Creamos el Flip Flop y lo conectamos con el cascaron
BasicDFF_enable FFD_conduc (.clk(clk), 
    .en(en), .d(d), .q(q));

initial begin
    $dumpfile("prueba1.vcd");//Guardamos los datos simulados en prueba.vcd
    $dumpvars(1, FFD_enable_tb);
    d=0; #9 d=1; #1 d=0; #1 d=1; #2 d=0; #1 d=1; #12 d=0;
        #1 d=1; #2 d=0; #1 d=1; #1 d=0; #1 d=1; #1 d=0; # 7 d=1;
        #8
    $stop;
    $finish;
end

endmodule

Proyecto Circuitos digitales/source/PARTE1/prueba2.vcd
$date
	Sat Dec 11 02:34:40 2021
$end
$version
	Icarus Verilog
$end
$timescale
	1ns
$end
$scope module FFD_enable_tb $end
$var wire 1 ! q $end
$var reg 1 " clk $end
$var reg 1 # d $end
$var reg 1 $ en $end
$upscope $end
$enddefinitions $end
#0
$dumpvars
1$
0#
1"
x!
$end
#1
0"
#2
1"
#3
0"
0$
#4
0!
1"
#5
0"
#6
1"
1$
#7
0"
#8
1"
#9
0"
0$
1#
#10
0!
1"
0#
#11
0"
1#
#12
1!
1"
1$
#13
0"
0#
#14
1"
1#
#15
0"
0$
#16
1"
#17
0"
#18
1"
1$
#19
0"
#20
1"
#21
0"
0$
#22
1"
#23
0"
#24
1"
1$
#25
0"
#26
1"
0#
#27
0"
1#
0$
#28
1"
#29
0"
0#
#30
1"
1#
1$
#31
0"
0#
#32
1"
1#
#33
0"
0#
0$
#34
0!
1"
#35
0"
#36
1"
1$
#37
0"
#38
1"
#39
0"
0$
#40
1!
1"
1#
#41
0"
#42
1"
1$
#43
0"
#44
1"
#45
0"
0$
#46
1"
#47
0"
#48
1"
1$
