Proyecto Circuitos digitales/Proyecto/source/256ram/mux.v
//Utilizamos un mux de 4x1 con un selector de 2 bits, salidas y entradas de 32 bits
module mux(
    input  [1:0]s,
    input  [31:0] i0, i1, i2, i3, 
    output reg [31:0] y
);
wire [1:0] a = (s==2'b00);
always @(*)
    begin
        if (s == 2'b00)y = i0;
    else if (s == 2'b01) y = i1;
    else if (s == 2'b10) y = i2;
    else if (s == 2'b11) y = i3;
    else y = y; // no change
    
    
   // $monitor("times=%0t y=0%0h s=0x%0b, i0=0x%0h LOG=0x%0b",$time,y,s,i0,a);
    
    end
endmodule

Proyecto Circuitos digitales/Proyecto/source/ram/ram.v
module ram
#(parameter BUS_WIDTH = 8)(
    // Inputs
    input clk,
    input [BUS_WIDTH-1:0] addr,
    input [31:0] dataIn,
    input wrEnable, // 0: Read, 1: Write
    // Outputs
    output reg [31:0] dataOut
);
reg [31:0] memory [0 : 2**BUS_WIDTH- 1];
initial begin
$readmemh("memory.hex", memory);
end
always @(posedge clk) begin
    if (wrEnable == 1'b1) memory[addr] = dataIn;
    else if (wrEnable == 1'b0) dataOut = memory[addr];
    else dataOut <= 32'bx;
end


endmodule

Proyecto Circuitos digitales/source/256ram/demux2.v
//Utilizamos un demux 1x4 con un select de tamaño 2 bits
//Se llamo demux1 el modulo y demux2 el archivo porque se habia creado otro demux que se elimino
module demux1(
    input Input,//wrEnable
    input [1:0] s,//select 
    output reg y1, y2, y3, y4
);

always @(Input) //Cada vez que la entrada (wrEnable) cambie, se actualizara los datos de salida para las rams
    begin
        if (s == 2'b00)
            begin 
            y1 = Input;
            {y2, y3, y4} = 0;//modo lectura
    else if (s == 2'b01) 
        begin
            y2 = Input;
            {y1, y3, y4} = 0;//modo lectura
        end
    else if (s == 2'b10) 
        begin
            y3 = Input;
            {y2, y1, y4} = 0;//modo lectura
        end
    else if (s == 2'b11) 
        begin
            y4 = Input;
            {y2, y3, y1} = 0;//modo lectura
        end
    else // no change 
        y1=y1;
        y2=y2;
        y3=y3;
        y4=y4;
    end

    //Se utilizo para hacer un debug de lo que pasaba dentro del demux
    //initial begin
    //    $monitor("times=%0t y1=0x%0h y2=0x%0h y3=0x%0h y4=0x%0h input=0x%0h s=0x%0b",$time,y1,y2,y3,y4,Input,s);
    //end
    
    
endmodule

Proyecto Circuitos digitales/source/256ram/256ram.v
`include "ram.v"
`include "mux.v"
`include "demux2.v"
module ram256
#(parameter BUS_WIDTH = 16)(
    // Inputs
    input clk,
    input [BUS_WIDTH-1:0] addr16,
    input [31:0] dataIn,
    input wrEnable, // 0: Read, 1: Write
    // Outputs
    output [31:0] dataOut
);


wire [31:0] dataOutA, dataOutB, dataOutC, dataOutD;//Cables para conectar salidas de las rams con el Mux
wire wireA, wireB, wireC, wireD;//Cables para conectar la salida del segundo Dmux con las rams
wire [1:0] s = addr16[15:14];//Valor de s1 y s2 
//Instancias 
//Demux_wrEnable
demux1 Dmux_wr(.Input(wrEnable), .s(s), .y1(wireA), .y2(wireB), .y3(wireC), .y4(wireD));
//RAMS 64kB
ram ramA (.clk(clk), .addr(addr16[13:0]), .dataIn(dataIn), .wrEnable(wireA), .dataOut(dataOutA));
ram ramB (.clk(clk), .addr(addr16[13:0]), .dataIn(dataIn), .wrEnable(wireB), .dataOut(dataOutB));
ram ramC (.clk(clk), .addr(addr16[13:0]), .dataIn(dataIn), .wrEnable(wireC), .dataOut(dataOutC));
ram ramD (.clk(clk), .addr(addr16[13:0]), .dataIn(dataIn), .wrEnable(wireD), .dataOut(dataOutD));
//Mux
mux Mux(.s(s), .i0(dataOutA), .i1(dataOutB), .i2(dataOutC), .i3(dataOutD), .y(dataOut));


endmodule

Proyecto Circuitos digitales/Proyecto/source/256ram/256ram_tb.v
//Se incluye la libreria de la ram de 256kB para un benchmark o test
`include "256ram.v"
//Escala de segundos en nanosegundos/ nanosegundos
`timescale 1 ns/ 1 ns 
//Creamos el cascaron
module ram256_tb;
    //dirreccion de bit 16s
    reg [15:0] addr16;
    //Dato que queremos escribir en la memoria si wrEnable=1
    reg [31:0] dataIn;
    reg wrEnable;
    //Dato que obtenemos por el addr16
    wire [31:0] dataOut;
    //Tiempos para la simulacion
    localparam period = 40;
    //Ciclo del reloj con un periodo de 40s
    reg clk;

    always begin
        clk = 1'b1; #20; // 20s en alto
        clk = 1'b0; #20; // 20s en bajo
    end

    //Conectamos el cascaron con la ram256 para probarla
    ram256 ram256test (
        .clk(clk),
        .addr16(addr16),
        .dataIn(dataIn),
        .wrEnable(wrEnable),
        .dataOut(dataOut)
    );


    initial begin
        $dumpfile("test2.vcd");//Guardamos los datos simulados en test2.vcd
        $dumpvars(0, ram256_tb); // Variables a guardar
        #period; #period; #period; // 60ns
        //Leemos y escribimos para primera ram00
        wrEnable = 0; 
        dataIn = 32'hCAFECAFE;
        addr16 = 16'h0003; // ram00 
        #period; #period; #period; //60s
        wrEnable = 1; 
        #period;#period;  
        wrEnable = 0;
        #period; #period; // 60s


        //Leemos y escribimos para segunda ram01
        wrEnable = 0;
        addr16= 16'h4003;
        #period; #period; #period;
        wrEnable = 1;
        #period; #period; 
        wrEnable = 0;
        #period; #period; // 60s


        //Leemos y escribimos para tercera ram10
        wrEnable = 0;
        addr16= 16'h8003 ;
        #period; #period; #period;
        wrEnable = 1;
        #period; #period; 
        wrEnable = 0;
        #period; #period; // 60s


         //Leemos y escribimos para tercera ram11
        wrEnable = 0;
        addr16= 16'hC003; 
        #period; #period; #period;
        wrEnable = 1;
        #period; #period; 
        wrEnable = 0;
        #period; #period; // 60s


        #period;

        //SEGUNDA RONDA////////////////////////////////////

        //Leemos y escribimos para primera ram00
        dataIn = 32'hBEBEBEBE;
        wrEnable = 0; 
        addr16 = 16'h3; // ram00 
        #period; #period; #period; //60s
        wrEnable = 1; 
        #period; #period; 
        wrEnable = 0;
        #period; #period; // 60s


        //Leemos y escribimos para segunda ram01
        wrEnable = 0;
        addr16= 16'h4003; 
        #period; #period; #period;
        wrEnable = 1;
        #period; #period; 
        wrEnable = 0;
        #period; #period; // 60s


        //Leemos y escribimos para tercera ram10
        wrEnable = 0;
        addr16= 16'h8003; 
        #period; #period; #period;
        wrEnable = 1;
        #period; #period; 
        wrEnable = 0;
        #period; #period; // 60s


         //Leemos y escribimos para tercera ram11
        wrEnable = 0;
        addr16= 16'hC003; 
        #period; #period; #period;
        wrEnable = 1;
        #period; #period; 
        wrEnable = 0;
        #period; #period; // 60s

        #period;
        
        $stop;
        $finish;

    end

endmodule

Proyecto Circuitos digitales/source/256ram/test2.vcd
$date
	Fri Dec 10 15:04:37 2021
$end
$version
	Icarus Verilog
$end
$timescale
	1ns
$end
$scope module ram256_tb $end
$var wire 32 ! dataOut [31:0] $end
$var reg 16 " addr16 [15:0] $end
$var reg 1 # clk $end
$var reg 32 $ dataIn [31:0] $end
$var reg 1 % wrEnable $end
$scope module ram256test $end
$var wire 16 & addr16 [15:0] $end
$var wire 1 # clk $end
$var wire 32 ' dataIn [31:0] $end
$var wire 1 % wrEnable $end
$var wire 1 ( wireD $end
$var wire 1 ) wireC $end
$var wire 1 * wireB $end
$var wire 1 + wireA $end
$var wire 2 , s [1:0] $end
$var wire 32 - dataOutD [31:0] $end
$var wire 32 . dataOutC [31:0] $end
$var wire 32 / dataOutB [31:0] $end
$var wire 32 0 dataOutA [31:0] $end
$var wire 32 1 dataOut [31:0] $end
$scope module Dmux_wr $end
$var wire 1 % Input $end
$var wire 2 2 s [1:0] $end
$var reg 1 + y1 $end
$var reg 1 * y2 $end
$var reg 1 ) y3 $end
$var reg 1 ( y4 $end
$upscope $end
$scope module Mux $end
$var wire 2 3 s [1:0] $end
$var wire 32 4 i3 [31:0] $end
$var wire 32 5 i2 [31:0] $end
$var wire 32 6 i1 [31:0] $end
$var wire 32 7 i0 [31:0] $end
$var wire 2 8 a [1:0] $end
$var reg 32 9 y [31:0] $end
$upscope $end
$scope module ramA $end
$var wire 14 : addr [13:0] $end
$var wire 1 # clk $end
$var wire 32 ; dataIn [31:0] $end
$var wire 1 + wrEnable $end
$var reg 32 < dataOut [31:0] $end
$upscope $end
$scope module ramB $end
$var wire 14 = addr [13:0] $end
$var wire 1 # clk $end
$var wire 32 > dataIn [31:0] $end
$var wire 1 * wrEnable $end
$var reg 32 ? dataOut [31:0] $end
$upscope $end
$scope module ramC $end
$var wire 14 @ addr [13:0] $end
$var wire 1 # clk $end
$var wire 32 A dataIn [31:0] $end
$var wire 1 ) wrEnable $end
$var reg 32 B dataOut [31:0] $end
$upscope $end
$scope module ramD $end
$var wire 14 C addr [13:0] $end
$var wire 1 # clk $end
$var wire 32 D dataIn [31:0] $end
$var wire 1 ( wrEnable $end
$var reg 32 E dataOut [31:0] $end
$upscope $end
$upscope $end
$upscope $end
$enddefinitions $end
#0
$dumpvars
bx E
bx D
bx C
bx B
bx A
bx @
bx ?
bx >
bx =
bx <
bx ;
bx :
bx 9
b0x 8
bx 7
bx 6
bx 5
bx 4
bx 3
bx 2
bx 1
bx 0
bx /
bx .
bx -
bx ,
x+
x*
x)
x(
bx '
bx &
x%
bx $
1#
bx "
bx !
$end
#20
0#
#40
1#
#60
0#
#80
1#
#100
0#
#120
b1 8
b0 ,
b0 2
b0 3
b11 :
b11 =
b11 @
b11 C
1#
b11 "
b11 &
b11001010111111101100101011111110 $
b11001010111111101100101011111110 '
b11001010111111101100101011111110 ;
b11001010111111101100101011111110 >
b11001010111111101100101011111110 A
b11001010111111101100101011111110 D
0%
#140
0#
#160
1#
#180
0#
#200
1#
#220
0#
#240
0*
0)
0(
1+
1#
1%
#260
0#
#280
1#
#300
0#
#320
b11001010111111101100101011111110 !
b11001010111111101100101011111110 1
b11001010111111101100101011111110 9
b11001010111111101100101011111110 0
b11001010111111101100101011111110 7
b11001010111111101100101011111110 <
0+
1#
0%
#340
0#
#360
1#
#380
0#
#400
bx !
bx 1
bx 9
b0 8
b1 ,
b1 2
b1 3
1#
b100000000000011 "
b100000000000011 &
#420
0#
#440
1#
#460
0#
#480
1#
#500
0#
#520
1*
1#
1%
#540
0#
#560
1#
#580
0#
#600
b11001010111111101100101011111110 !
b11001010111111101100101011111110 1
b11001010111111101100101011111110 9
b11001010111111101100101011111110 /
b11001010111111101100101011111110 6
b11001010111111101100101011111110 ?
0*
1#
0%
#620
0#
#640
1#
#660
0#
#680
bx !
bx 1
bx 9
b10 ,
b10 2
b10 3
1#
b1000000000000011 "
b1000000000000011 &
#700
0#
#720
1#
#740
0#
#760
1#
#780
0#
#800
1)
1#
1%
#820
0#
#840
1#
#860
0#
#880
b11001010111111101100101011111110 !
b11001010111111101100101011111110 1
b11001010111111101100101011111110 9
b11001010111111101100101011111110 .
b11001010111111101100101011111110 5
b11001010111111101100101011111110 B
0)
1#
0%
#900
0#
#920
1#
#940
0#
#960
bx !
bx 1
bx 9
b11 ,
b11 2
b11 3
1#
b1100000000000011 "
b1100000000000011 &
#980
0#
#1000
1#
#1020
0#
#1040
1#
#1060
0#
#1080
1(
1#
1%
#1100
0#
#1120
1#
#1140
0#
#1160
b11001010111111101100101011111110 !
b11001010111111101100101011111110 1
b11001010111111101100101011111110 9
b11001010111111101100101011111110 -
b11001010111111101100101011111110 4
b11001010111111101100101011111110 E
0(
1#
0%
#1180
0#
#1200
1#
#1220
0#
#1240
1#
#1260
0#
#1280
b1 8
b0 ,
b0 2
b0 3
1#
b11 "
b11 &
b10111110101111101011111010111110 $
b10111110101111101011111010111110 '
b10111110101111101011111010111110 ;
b10111110101111101011111010111110 >
b10111110101111101011111010111110 A
b10111110101111101011111010111110 D
#1300
0#
#1320
1#
#1340
0#
#1360
1#
#1380
0#
#1400
1+
1#
1%
#1420
0#
#1440
1#
#1460
0#
#1480
b10111110101111101011111010111110 !
b10111110101111101011111010111110 1
b10111110101111101011111010111110 9
b10111110101111101011111010111110 0
b10111110101111101011111010111110 7
b10111110101111101011111010111110 <
0+
1#
0%
#1500
0#
#1520
1#
#1540
0#
#1560
b11001010111111101100101011111110 !
b11001010111111101100101011111110 1
b11001010111111101100101011111110 9
b0 8
b1 ,
b1 2
b1 3
1#
b100000000000011 "
b100000000000011 &
#1580
0#
#1600
1#
#1620
0#
#1640
1#
#1660
0#
#1680
1*
1#
1%
#1700
0#
#1720
1#
#1740
0#
#1760
b10111110101111101011111010111110 !
b10111110101111101011111010111110 1
b10111110101111101011111010111110 9
b10111110101111101011111010111110 /
b10111110101111101011111010111110 6
b10111110101111101011111010111110 ?
0*
1#
0%
#1780
0#
#1800
1#
#1820
0#
#1840
b11001010111111101100101011111110 !
b11001010111111101100101011111110 1
b11001010111111101100101011111110 9
b10 ,
b10 2
b10 3
1#
b1000000000000011 "
b1000000000000011 &
#1860
0#
#1880
1#
#1900
0#
#1920
1#
#1940
0#
#1960
1)
1#
1%
#1980
0#
#2000
1#
#2020
0#
#2040
b10111110101111101011111010111110 !
b10111110101111101011111010111110 1
b10111110101111101011111010111110 9
b10111110101111101011111010111110 .
b10111110101111101011111010111110 5
b10111110101111101011111010111110 B
0)
1#
0%
#2060
0#
#2080
1#
#2100
0#
#2120
b11001010111111101100101011111110 !
b11001010111111101100101011111110 1
b11001010111111101100101011111110 9
b11 ,
b11 2
b11 3
1#
b1100000000000011 "
b1100000000000011 &
#2140
0#
#2160
1#
#2180
0#
#2200
1#
#2220
0#
#2240
1(
1#
1%
#2260
0#
#2280
1#
#2300
0#
#2320
b10111110101111101011111010111110 !
b10111110101111101011111010111110 1
b10111110101111101011111010111110 9
b10111110101111101011111010111110 -
b10111110101111101011111010111110 4
b10111110101111101011111010111110 E
0(
1#
0%
#2340
0#
#2360
1#
#2380
0#
#2400
bx !
bx 1
bx 9
bx 0
bx 7
bx <
bx /
bx 6
bx ?
bx .
bx 5
bx B
bx -
bx 4
bx E
b1 8
b0 ,
b0 2
b0 3
b101 :
b101 =
b101 @
b101 C
1#
b101 "
b101 &
b11001010111111101100101011111110 $
b11001010111111101100101011111110 '
b11001010111111101100101011111110 ;
b11001010111111101100101011111110 >
b11001010111111101100101011111110 A
b11001010111111101100101011111110 D
#2420
0#
#2440
1#
#2460
0#
#2480
1#
#2500
0#
#2520
1+
1#
1%
#2540
0#
#2560
1#
#2580
0#
#2600
b11001010111111101100101011111110 !
b11001010111111101100101011111110 1
b11001010111111101100101011111110 9
b11001010111111101100101011111110 0
b11001010111111101100101011111110 7
b11001010111111101100101011111110 <
0+
1#
0%
#2620
0#
#2640
1#
#2660
0#
#2680
b10111110101111101011111010111110 !
b10111110101111101011111010111110 1
b10111110101111101011111010111110 9
b10111110101111101011111010111110 -
b10111110101111101011111010111110 4
b10111110101111101011111010111110 E
b10111110101111101011111010111110 .
b10111110101111101011111010111110 5
b10111110101111101011111010111110 B
b10111110101111101011111010111110 /
b10111110101111101011111010111110 6
b10111110101111101011111010111110 ?
b10111110101111101011111010111110 0
b10111110101111101011111010111110 7
b10111110101111101011111010111110 <
b11 :
b11 =
b11 @
b11 C
1#
b11 "
b11 &
#2700
0#
#2720
1#
#2740
0#
#2760
1#
#2780
0#
#2800
1+
1#
1%
#2820
0#
#2840
1#
#2860
0#
#2880
b11001010111111101100101011111110 !
b11001010111111101100101011111110 1
b11001010111111101100101011111110 9
b11001010111111101100101011111110 0
b11001010111111101100101011111110 7
b11001010111111101100101011111110 <
0+
1#
0%
#2900
0#
#2920
1#
#2940
0#
#2960
bx !
bx 1
bx 9
bx /
bx 6
bx ?
bx .
bx 5
bx B
bx -
bx 4
bx E
b0 8
b1 ,
b1 2
b1 3
b101 :
b101 =
b101 @
b101 C
1#
b100000000000101 "
b100000000000101 &
#2980
0#
#3000
1#
#3020
0#
#3040
1#
#3060
0#
#3080
1*
1#
1%
#3100
0#
#3120
1#
#3140
0#
#3160
b11001010111111101100101011111110 !
b11001010111111101100101011111110 1
b11001010111111101100101011111110 9
b11001010111111101100101011111110 /
b11001010111111101100101011111110 6
b11001010111111101100101011111110 ?
0*
1#
0%
#3180
0#
#3200
1#
#3220
0#
#3240
b10111110101111101011111010111110 !
b10111110101111101011111010111110 1
b10111110101111101011111010111110 9
b10111110101111101011111010111110 -
b10111110101111101011111010111110 4
b10111110101111101011111010111110 E
b10111110101111101011111010111110 .
b10111110101111101011111010111110 5
b10111110101111101011111010111110 B
b10111110101111101011111010111110 /
b10111110101111101011111010111110 6
b10111110101111101011111010111110 ?
b11 :
b11 =
b11 @
b11 C
1#
b100000000000011 "
b100000000000011 &
#3260
0#
#3280
1#
#3300
0#
#3320
1#
#3340
0#
#3360
1*
1#
1%
#3380
0#
#3400
1#
#3420
0#
#3440
b11001010111111101100101011111110 !
b11001010111111101100101011111110 1
b11001010111111101100101011111110 9
b11001010111111101100101011111110 /
b11001010111111101100101011111110 6
b11001010111111101100101011111110 ?
0*
1#
0%
